{
  "manifestVersion": "3.2",
  "admin": {
    "address": "0x844da4Df48db7fE8d1e9b0D783222ba5C28A323c",
    "txHash": "0x88ffc0a697183c3eee7d2b5eb35e6ad1cb49853767ae0e292458ef3f87f263e0"
  },
  "proxies": [
    {
      "address": "0xC762b2b5C7829C3a914E46D87489BCfc7a22e4b1",
      "txHash": "0x897524aaf7250894da4cc5776e67bd259ccfcfee262fd4becbf1d2eaa0a17332",
      "kind": "transparent"
    }
  ],
  "impls": {
    "d03ed9704f0c07b3dc41448b692e5abaa63146a37d9d70d7f559f05815229c6e": {
      "address": "0xe8D06798fdaF613E60e6C300bE9e412877b67DC1",
      "txHash": "0xe88b3c44345c0f1695d6a846e307ccd95537c4d1e765dd27e20b5c6a963dd5a9",
      "layout": {
        "solcVersion": "0.8.17",
        "storage": [
          {
            "label": "_initialized",
            "offset": 0,
            "slot": "0",
            "type": "t_uint8",
            "contract": "Initializable",
            "src": "@openzeppelin/contracts-upgradeable/proxy/utils/Initializable.sol:63",
            "retypedFrom": "bool"
          },
          {
            "label": "_initializing",
            "offset": 1,
            "slot": "0",
            "type": "t_bool",
            "contract": "Initializable",
            "src": "@openzeppelin/contracts-upgradeable/proxy/utils/Initializable.sol:68"
          },
          {
            "label": "__gap",
            "offset": 0,
            "slot": "1",
            "type": "t_array(t_uint256)50_storage",
            "contract": "ContextUpgradeable",
            "src": "@openzeppelin/contracts-upgradeable/utils/ContextUpgradeable.sol:36"
          },
          {
            "label": "__gap",
            "offset": 0,
            "slot": "51",
            "type": "t_array(t_uint256)50_storage",
            "contract": "ERC165Upgradeable",
            "src": "@openzeppelin/contracts-upgradeable/utils/introspection/ERC165Upgradeable.sol:41"
          },
          {
            "label": "_roles",
            "offset": 0,
            "slot": "101",
            "type": "t_mapping(t_bytes32,t_struct(RoleData)793_storage)",
            "contract": "AccessControlUpgradeable",
            "src": "@openzeppelin/contracts-upgradeable/access/AccessControlUpgradeable.sol:62"
          },
          {
            "label": "__gap",
            "offset": 0,
            "slot": "102",
            "type": "t_array(t_uint256)49_storage",
            "contract": "AccessControlUpgradeable",
            "src": "@openzeppelin/contracts-upgradeable/access/AccessControlUpgradeable.sol:260"
          },
          {
            "label": "_pendingDefaultAdmin",
            "offset": 0,
            "slot": "151",
            "type": "t_address",
            "contract": "AccessControlDefaultAdminRulesUpgradeable",
            "src": "@openzeppelin/contracts-upgradeable/access/AccessControlDefaultAdminRulesUpgradeable.sol:43"
          },
          {
            "label": "_pendingDefaultAdminSchedule",
            "offset": 20,
            "slot": "151",
            "type": "t_uint48",
            "contract": "AccessControlDefaultAdminRulesUpgradeable",
            "src": "@openzeppelin/contracts-upgradeable/access/AccessControlDefaultAdminRulesUpgradeable.sol:44"
          },
          {
            "label": "_currentDelay",
            "offset": 26,
            "slot": "151",
            "type": "t_uint48",
            "contract": "AccessControlDefaultAdminRulesUpgradeable",
            "src": "@openzeppelin/contracts-upgradeable/access/AccessControlDefaultAdminRulesUpgradeable.sol:46"
          },
          {
            "label": "_currentDefaultAdmin",
            "offset": 0,
            "slot": "152",
            "type": "t_address",
            "contract": "AccessControlDefaultAdminRulesUpgradeable",
            "src": "@openzeppelin/contracts-upgradeable/access/AccessControlDefaultAdminRulesUpgradeable.sol:47"
          },
          {
            "label": "_pendingDelay",
            "offset": 20,
            "slot": "152",
            "type": "t_uint48",
            "contract": "AccessControlDefaultAdminRulesUpgradeable",
            "src": "@openzeppelin/contracts-upgradeable/access/AccessControlDefaultAdminRulesUpgradeable.sol:50"
          },
          {
            "label": "_pendingDelaySchedule",
            "offset": 26,
            "slot": "152",
            "type": "t_uint48",
            "contract": "AccessControlDefaultAdminRulesUpgradeable",
            "src": "@openzeppelin/contracts-upgradeable/access/AccessControlDefaultAdminRulesUpgradeable.sol:51"
          },
          {
            "label": "__gap",
            "offset": 0,
            "slot": "153",
            "type": "t_array(t_uint256)48_storage",
            "contract": "AccessControlDefaultAdminRulesUpgradeable",
            "src": "@openzeppelin/contracts-upgradeable/access/AccessControlDefaultAdminRulesUpgradeable.sol:394"
          },
          {
            "label": "_paused",
            "offset": 0,
            "slot": "201",
            "type": "t_bool",
            "contract": "PausableUpgradeable",
            "src": "@openzeppelin/contracts-upgradeable/security/PausableUpgradeable.sol:29"
          },
          {
            "label": "__gap",
            "offset": 0,
            "slot": "202",
            "type": "t_array(t_uint256)49_storage",
            "contract": "PausableUpgradeable",
            "src": "@openzeppelin/contracts-upgradeable/security/PausableUpgradeable.sol:116"
          },
          {
            "label": "_index",
            "offset": 0,
            "slot": "251",
            "type": "t_uint256",
            "contract": "DLCManager",
            "src": "contracts/DLCManager.sol:47"
          },
          {
            "label": "dlcs",
            "offset": 0,
            "slot": "252",
            "type": "t_mapping(t_uint256,t_struct(DLC)10253_storage)",
            "contract": "DLCManager",
            "src": "contracts/DLCManager.sol:48"
          },
          {
            "label": "dlcIDsByUUID",
            "offset": 0,
            "slot": "253",
            "type": "t_mapping(t_bytes32,t_uint256)",
            "contract": "DLCManager",
            "src": "contracts/DLCManager.sol:49"
          }
        ],
        "types": {
          "t_address": {
            "label": "address",
            "numberOfBytes": "20"
          },
          "t_array(t_uint256)48_storage": {
            "label": "uint256[48]",
            "numberOfBytes": "1536"
          },
          "t_array(t_uint256)49_storage": {
            "label": "uint256[49]",
            "numberOfBytes": "1568"
          },
          "t_array(t_uint256)50_storage": {
            "label": "uint256[50]",
            "numberOfBytes": "1600"
          },
          "t_bool": {
            "label": "bool",
            "numberOfBytes": "1"
          },
          "t_bytes32": {
            "label": "bytes32",
            "numberOfBytes": "32"
          },
          "t_enum(DLCStatus)10225": {
            "label": "enum DLCLink.DLCStatus",
            "members": [
              "READY",
              "FUNDED",
              "CLOSING",
              "CLOSED"
            ],
            "numberOfBytes": "1"
          },
          "t_mapping(t_address,t_bool)": {
            "label": "mapping(address => bool)",
            "numberOfBytes": "32"
          },
          "t_mapping(t_bytes32,t_struct(RoleData)793_storage)": {
            "label": "mapping(bytes32 => struct AccessControlUpgradeable.RoleData)",
            "numberOfBytes": "32"
          },
          "t_mapping(t_bytes32,t_uint256)": {
            "label": "mapping(bytes32 => uint256)",
            "numberOfBytes": "32"
          },
          "t_mapping(t_uint256,t_struct(DLC)10253_storage)": {
            "label": "mapping(uint256 => struct DLCLink.DLC)",
            "numberOfBytes": "32"
          },
          "t_string_storage": {
            "label": "string",
            "numberOfBytes": "32"
          },
          "t_struct(DLC)10253_storage": {
            "label": "struct DLCLink.DLC",
            "members": [
              {
                "label": "uuid",
                "type": "t_bytes32",
                "offset": 0,
                "slot": "0"
              },
              {
                "label": "protocolWallet",
                "type": "t_address",
                "offset": 0,
                "slot": "1"
              },
              {
                "label": "protocolContract",
                "type": "t_address",
                "offset": 0,
                "slot": "2"
              },
              {
                "label": "timestamp",
                "type": "t_uint256",
                "offset": 0,
                "slot": "3"
              },
              {
                "label": "valueLocked",
                "type": "t_uint256",
                "offset": 0,
                "slot": "4"
              },
              {
                "label": "refundDelay",
                "type": "t_uint256",
                "offset": 0,
                "slot": "5"
              },
              {
                "label": "creator",
                "type": "t_address",
                "offset": 0,
                "slot": "6"
              },
              {
                "label": "outcome",
                "type": "t_uint256",
                "offset": 0,
                "slot": "7"
              },
              {
                "label": "status",
                "type": "t_enum(DLCStatus)10225",
                "offset": 0,
                "slot": "8"
              },
              {
                "label": "fundingTxId",
                "type": "t_string_storage",
                "offset": 0,
                "slot": "9"
              },
              {
                "label": "closingTxId",
                "type": "t_string_storage",
                "offset": 0,
                "slot": "10"
              },
              {
                "label": "btcFeeRecipient",
                "type": "t_string_storage",
                "offset": 0,
                "slot": "11"
              },
              {
                "label": "btcFeeBasisPoints",
                "type": "t_uint256",
                "offset": 0,
                "slot": "12"
              }
            ],
            "numberOfBytes": "416"
          },
          "t_struct(RoleData)793_storage": {
            "label": "struct AccessControlUpgradeable.RoleData",
            "members": [
              {
                "label": "members",
                "type": "t_mapping(t_address,t_bool)",
                "offset": 0,
                "slot": "0"
              },
              {
                "label": "adminRole",
                "type": "t_bytes32",
                "offset": 0,
                "slot": "1"
              }
            ],
            "numberOfBytes": "64"
          },
          "t_uint256": {
            "label": "uint256",
            "numberOfBytes": "32"
          },
          "t_uint48": {
            "label": "uint48",
            "numberOfBytes": "6"
          },
          "t_uint8": {
            "label": "uint8",
            "numberOfBytes": "1"
          }
        },
        "namespaces": {}
      }
    }
  }
}
